oak_build/__init__.py
oak_build/app.py
oak_build/app_logging.py
oak_build/decorators.py
oak_build/direcory_exec_context.py
oak_build/main.py
oak_build/oak_file.py
oak_build/parsers.py
oak_build/task_runner.py
oak_build/tools/shell.py
oak_build-0.1.2.post2.dist-info/LICENSE
oak_build-0.1.2.post2.dist-info/WHEEL
oak_build-0.1.2.post2.dist-info/METADATA
oak_build-0.1.2.post2.dist-info/entry_points.txt
oak_build-0.1.2.post2.dist-info/RECORD
